icut/__init__.py
icut-0.0.4.dist-info/LICENSE
icut-0.0.4.dist-info/METADATA
icut-0.0.4.dist-info/WHEEL
icut-0.0.4.dist-info/top_level.txt
icut-0.0.4.dist-info/RECORD
