Metadata-Version: 2.1
Name: icut
Version: 0.0.4
Summary: A fast Thai tokenization library
Home-page: https://github.com/korakot/icut
Author: Korakot Chaovavanich
Author-email: korakot@gmail.com
License: UNKNOWN
Platform: UNKNOWN
Classifier: Programming Language :: Python :: 3
Classifier: License :: OSI Approved :: MIT License
Classifier: Operating System :: OS Independent
Requires-Python: >=3.6
Requires-Dist: pyicu
